e2e/__init__.py
e2e/_version.py
e2e/crc.cp314t-win32.pyd
e2e/crc.pyi
e2e/p01.cp314t-win32.pyd
e2e/p01.pyi
e2e/p02.cp314t-win32.pyd
e2e/p02.pyi
e2e/p04.cp314t-win32.pyd
e2e/p04.pyi
e2e/p05.cp314t-win32.pyd
e2e/p05.pyi
e2e/p06.cp314t-win32.pyd
e2e/p06.pyi
e2e/p07.cp314t-win32.pyd
e2e/p07.pyi
e2e/py.typed
autosar_e2e-0.7.0.dist-info/METADATA
autosar_e2e-0.7.0.dist-info/WHEEL
autosar_e2e-0.7.0.dist-info/licenses/LICENSE.txt
autosar_e2e-0.7.0.dist-info/RECORD
