Metadata-Version: 2.2
Name: autosar-e2e
Version: 0.7.0
Summary: Python implementation of the AUTOSAR E2E Protocol
Keywords: AUTOSAR,E2E,automotive
Author-Email: Artur Drogunow <artur.drogunow@zf.com>
License: MIT
Classifier: Development Status :: 5 - Production/Stable
Classifier: Programming Language :: Python
Classifier: Programming Language :: Python :: 3.7
Classifier: Programming Language :: Python :: 3.8
Classifier: Programming Language :: Python :: 3.9
Classifier: Programming Language :: Python :: 3.10
Classifier: Programming Language :: Python :: 3.11
Classifier: Programming Language :: Python :: 3.12
Classifier: Programming Language :: Python :: 3.13
Classifier: Programming Language :: Python :: Implementation :: CPython
Classifier: Programming Language :: Python :: Implementation :: PyPy
Classifier: Programming Language :: Python :: Free Threading :: 1 - Unstable
Project-URL: Documentation, https://autosar-e2e.readthedocs.io/en/latest
Project-URL: Issues, https://github.com/zariiii9003/autosar-e2e/issues
Project-URL: Source, https://github.com/zariiii9003/autosar-e2e
Project-URL: Homepage, https://github.com/zariiii9003/autosar-e2e
Requires-Python: >=3.7
